Grading/Grading.py
Grading/__init__.py
Grading/py.typed
grading_harness_sebastian_stigler-0.2.0.dist-info/METADATA
grading_harness_sebastian_stigler-0.2.0.dist-info/WHEEL
grading_harness_sebastian_stigler-0.2.0.dist-info/RECORD
