Metadata-Version: 2.4
Name: grading-harness-sebastian-stigler
Version: 0.2.0
Summary: Harmness for grading assignments for TuD Lecture
Author-email: Sebastian Stigler <sebastian.stigler@hs-aalen.de>
Requires-Python: >=3.13
